{
  "ad1":[
     {
      "des": "",
      "banner": "",
      "image_path": "https://play-lh.googleusercontent.com/pSfg-eOHiclY1_NMcP65a6GphAmEk0H-O5XFmE4PhUMrGuyybF-OgnryYiDP8HHAgZ0F=s180-rw",
      "ads_name": "Picasoo Live Tv",
      "ads_Link": "https://play.google.com/store/apps/details?id=picasoo.picasootv.cricket.livetv.pikasshow.picasootvguide.picasootv01"
    },
     {
      "des": "",
      "banner": "",
      "image_path": "https://play-lh.googleusercontent.com/N0bkNrK0V0ajT9X0_LUyfAPl470Sqq7Z_YW59NbbkcHZuz_mBPYMnerafRJy3xVwIw=s180-rw",
      "ads_name": "United Menu",
      "ads_Link": "https://play.google.com/store/apps/details?id=united.menu.freeadvice.united.menu.freeadvice05"
    },
     {
      "des": "",
      "banner": "",
      "image_path": "https://play-lh.googleusercontent.com/zVJsOkhufU9zIFAiglopEEPu1xXJJ6aHmVfE7mhTXALNgbeo3y8OxJZwnW97NdthNg=s180-rw",
      "ads_name": "Winzoo Games, Play & Win Walkt",
      "ads_Link": "https://play.google.com/store/apps/details?id=winzo.winzogold.winzogold.earncoins.freewinzo.winzoapp02"
    },
     {
      "des": "",
      "banner": "",
      "image_path": "https://play-lh.googleusercontent.com/N0bkNrK0V0ajT9X0_LUyfAPl470Sqq7Z_YW59NbbkcHZuz_mBPYMnerafRJy3xVwIw=s180-rw",
      "ads_name": "United Menu",
      "ads_Link": "https://play.google.com/store/apps/details?id=united.menu.freeadvice.united.menu.freeadvice06"
    },

     {
      "des": "",
      "banner": "",
      "image_path": "https://happymod.com/static/img/logo.png",
      "ads_name": "Happy Mod",
      "ads_Link": "https://play.google.com/store/apps/details?id=happymod.happymod.happymod.freegame.happymod.mod.tips.happymod12"
    },

     {
      "des": "",
      "banner": "",
      "image_path": "https://play-lh.googleusercontent.com/LB7uBB78JN8aRhPOiqmjuuNOznAweFwrdzzOJlBxWcWXN1dKpsDbbR9UFe21qUf0ag=s180-rw",
      "ads_name": "Picasoo Tve",
      "ads_Link": "https://play.google.com/store/apps/details?id=pikashowtv.picasso.pikashwlivetv.alltvshow.pikashowtv.tv11"
    },

    
     {
      "des": "",
      "banner": "",
      "image_path": "https://play-lh.googleusercontent.com/W74S5DgCOQ5o4-p8HtRvhw54rPZAYqSUFDTKkLhrOggWZKEANG0WBjzDFkJV1NReoGM=s180-rw",
      "ads_name": "Airtel Tv",
      "ads_Link": "https://play.google.com/store/apps/details?id=airteltv.airteltvlive.freeairteltvsportsapp.freetv.freeairteltv.airtel02"
    },

     {
      "des": "",
      "banner": "",
      "image_path": "https://play-lh.googleusercontent.com/YUqcAXu2krRmhAQXupeTD5VhHXFxpv3oHVQtBRwCm2t54PDdA9cwjcmi6_reuItTKA=s180-rw",
      "ads_name": "Lulubox",
      "ads_Link": "https://play.google.com/store/apps/details?id=lulubox.lulubox.lulubox.newluluboxappsfreefire.luluboxskintool.tips.lulubox01"
    },

     {
      "des": "",
      "banner": "",
      "image_path": "https://play-lh.googleusercontent.com/m7UzuFoXqeQUzdI0FRjI4peJo901tFPDgHJpnFEXHgywmgPJMYa55g6Yr-ZrmQ6DcPg=s180-rw",
      "ads_name": "Unlimited coin for 8 ball pool walkthrough",
      "ads_Link": "https://play.google.com/store/apps/details?id=unlimitedcoinfor8ballpoolwalkthroug.eightballpool04"
    },
      {
      "des": "",
      "banner": "https://i.git99.com/upload/android/icon/2018/04/03/6273c218dcfb83558dd6032b8f89f8af.jpg",
      "image_path": "https://play-lh.googleusercontent.com/Fj6bAxj8tyV084nxYpw8TP0sDJkJEsSmTxL7HTyLkv-50cly4Vw-WM6Ev4_Hepjryg=s180-rw",
      "ads_name": "Grand City Theft Autos",
      "ads_Link": "https://play.google.com/store/apps/details?id=grandcitycheats.tipsgrandcityautos.grandtheftautocity.grandcityautos.Guide01"
    }
     ]
}
